{
  "feedsList": [
    {
      "id": 99,
      "nickname": "hihi",
      "profile_image": "",
      "img_url": "https://photofolio.s3.ap-northeast-2.amazonaws.com/1667973815981.jpg",
      "title": "11월 8일 9",
      "IFNULL(a.comment_cnt, '0')": "0",
      "IFNULL(b.sympathy_cnt, '0')": "0",
      "view_count": 0,
      "created_at": "2022-11-09"
    },
    {
      "id": 98,
      "nickname": "hihi",
      "profile_image": "",
      "img_url": "https://photofolio.s3.ap-northeast-2.amazonaws.com/1667966857038.jpg",
      "title": "11월 8일 6",
      "IFNULL(a.comment_cnt, '0')": "0",
      "IFNULL(b.sympathy_cnt, '0')": "0",
      "view_count": 0,
      "created_at": "2022-11-09"
    },
    {
      "id": 97,
      "nickname": "hihi",
      "profile_image": "",
      "img_url": "https://photofolio.s3.ap-northeast-2.amazonaws.com/1667966845327.jpg",
      "title": "11월 8일 5",
      "IFNULL(a.comment_cnt, '0')": "0",
      "IFNULL(b.sympathy_cnt, '0')": "0",
      "view_count": 0,
      "created_at": "2022-11-09"
    },
    {
      "id": 96,
      "nickname": "hihi",
      "profile_image": "",
      "img_url": "https://photofolio.s3.ap-northeast-2.amazonaws.com/1667966773730.jpg",
      "title": "11월 8일 4",
      "IFNULL(a.comment_cnt, '0')": "0",
      "IFNULL(b.sympathy_cnt, '0')": "0",
      "view_count": 0,
      "created_at": "2022-11-09"
    },
    {
      "id": 95,
      "nickname": "hihi",
      "profile_image": "",
      "img_url": "https://photofolio.s3.ap-northeast-2.amazonaws.com/1667966758613.jpg",
      "title": "11월 8일 3",
      "IFNULL(a.comment_cnt, '0')": "0",
      "IFNULL(b.sympathy_cnt, '0')": "0",
      "view_count": 0,
      "created_at": "2022-11-09"
    },
    {
      "id": 94,
      "nickname": "jhhhhhhhh",
      "profile_image": "https://photofolio.s3.ap-northeast-2.amazonaws.com/1667958023171.png",
      "img_url": "https://photofolio.s3.ap-northeast-2.amazonaws.com/1667959151596.png",
      "title": "test",
      "IFNULL(a.comment_cnt, '0')": "0",
      "IFNULL(b.sympathy_cnt, '0')": "0",
      "view_count": 0,
      "created_at": "2022-11-09"
    },
    {
      "id": 93,
      "nickname": "jhhhhhhhh",
      "profile_image": "https://photofolio.s3.ap-northeast-2.amazonaws.com/1667958023171.png",
      "img_url": "https://photofolio.s3.ap-northeast-2.amazonaws.com/1667959065227.png",
      "title": "asdf",
      "IFNULL(a.comment_cnt, '0')": "0",
      "IFNULL(b.sympathy_cnt, '0')": "0",
      "view_count": 0,
      "created_at": "2022-11-09"
    },
    {
      "id": 92,
      "nickname": "hihi",
      "profile_image": "",
      "img_url": "https://photofolio.s3.ap-northeast-2.amazonaws.com/1667958875369.jpg",
      "title": "11월 8일 2",
      "IFNULL(a.comment_cnt, '0')": "0",
      "IFNULL(b.sympathy_cnt, '0')": "0",
      "view_count": 0,
      "created_at": "2022-11-09"
    },
    {
      "id": 91,
      "nickname": "hihi",
      "profile_image": "",
      "img_url": "https://photofolio.s3.ap-northeast-2.amazonaws.com/1667885056037.jpg",
      "title": "11월 8일 ",
      "IFNULL(a.comment_cnt, '0')": "0",
      "IFNULL(b.sympathy_cnt, '0')": "0",
      "view_count": 0,
      "created_at": "2022-11-08"
    },
    {
      "id": 90,
      "nickname": "undefined",
      "profile_image": "https://photofolio.s3.ap-northeast-2.amazonaws.com/1667872584687.jpg",
      "img_url": "https://photofolio.s3.ap-northeast-2.amazonaws.com/1667879970652.jpg",
      "title": "11월 7일 22dd",
      "IFNULL(a.comment_cnt, '0')": "0",
      "IFNULL(b.sympathy_cnt, '0')": "0",
      "view_count": 0,
      "created_at": "2022-11-08"
    },
    {
      "id": 89,
      "nickname": "undefined",
      "profile_image": "https://photofolio.s3.ap-northeast-2.amazonaws.com/1667872584687.jpg",
      "img_url": null,
      "title": "11월 7일 22d",
      "IFNULL(a.comment_cnt, '0')": "0",
      "IFNULL(b.sympathy_cnt, '0')": "0",
      "view_count": 0,
      "created_at": "2022-11-08"
    },
    {
      "id": 88,
      "nickname": "undefined",
      "profile_image": "https://photofolio.s3.ap-northeast-2.amazonaws.com/1667872584687.jpg",
      "img_url": null,
      "title": "11월 7일 22",
      "IFNULL(a.comment_cnt, '0')": "0",
      "IFNULL(b.sympathy_cnt, '0')": "0",
      "view_count": 0,
      "created_at": "2022-11-08"
    },
    {
      "id": 87,
      "nickname": "undefined",
      "profile_image": "https://photofolio.s3.ap-northeast-2.amazonaws.com/1667724350149.jpg",
      "img_url": "https://photofolio.s3.ap-northeast-2.amazonaws.com/1667820712248.jpg",
      "title": "11월 7일 21",
      "IFNULL(a.comment_cnt, '0')": "0",
      "IFNULL(b.sympathy_cnt, '0')": "0",
      "view_count": 0,
      "created_at": "2022-11-07"
    },
    {
      "id": 86,
      "nickname": "undefined",
      "profile_image": "https://photofolio.s3.ap-northeast-2.amazonaws.com/1667724350149.jpg",
      "img_url": "https://photofolio.s3.ap-northeast-2.amazonaws.com/1667817592538.png",
      "title": "11월 7일 20",
      "IFNULL(a.comment_cnt, '0')": "0",
      "IFNULL(b.sympathy_cnt, '0')": "0",
      "view_count": 0,
      "created_at": "2022-11-07"
    },
    {
      "id": 85,
      "nickname": "undefined",
      "profile_image": "https://photofolio.s3.ap-northeast-2.amazonaws.com/1667724350149.jpg",
      "img_url": "https://photofolio.s3.ap-northeast-2.amazonaws.com/1667811617724.png",
      "title": "11월 7일 19",
      "IFNULL(a.comment_cnt, '0')": "0",
      "IFNULL(b.sympathy_cnt, '0')": "0",
      "view_count": 0,
      "created_at": "2022-11-07"
    },
    {
      "id": 84,
      "nickname": "undefined",
      "profile_image": "https://photofolio.s3.ap-northeast-2.amazonaws.com/1667724350149.jpg",
      "img_url": "https://photofolio.s3.ap-northeast-2.amazonaws.com/1667811571339.png",
      "title": "11월 7일 18",
      "IFNULL(a.comment_cnt, '0')": "0",
      "IFNULL(b.sympathy_cnt, '0')": "0",
      "view_count": 0,
      "created_at": "2022-11-07"
    },
    {
      "id": 83,
      "nickname": "undefined",
      "profile_image": "https://photofolio.s3.ap-northeast-2.amazonaws.com/1667724350149.jpg",
      "img_url": "https://photofolio.s3.ap-northeast-2.amazonaws.com/1667811395340.png",
      "title": "11월 7일 17",
      "IFNULL(a.comment_cnt, '0')": "0",
      "IFNULL(b.sympathy_cnt, '0')": "0",
      "view_count": 0,
      "created_at": "2022-11-07"
    },
    {
      "id": 82,
      "nickname": "undefined",
      "profile_image": "https://photofolio.s3.ap-northeast-2.amazonaws.com/1667724350149.jpg",
      "img_url": "https://photofolio.s3.ap-northeast-2.amazonaws.com/1667811316568.png",
      "title": "11월 7일 16",
      "IFNULL(a.comment_cnt, '0')": "0",
      "IFNULL(b.sympathy_cnt, '0')": "0",
      "view_count": 0,
      "created_at": "2022-11-07"
    },
    {
      "id": 81,
      "nickname": "undefined",
      "profile_image": "https://photofolio.s3.ap-northeast-2.amazonaws.com/1667724350149.jpg",
      "img_url": "https://photofolio.s3.ap-northeast-2.amazonaws.com/1667811227253.png",
      "title": "11월 7일 15",
      "IFNULL(a.comment_cnt, '0')": "0",
      "IFNULL(b.sympathy_cnt, '0')": "0",
      "view_count": 0,
      "created_at": "2022-11-07"
    },
    {
      "id": 80,
      "nickname": "undefined",
      "profile_image": "https://photofolio.s3.ap-northeast-2.amazonaws.com/1667724350149.jpg",
      "img_url": "https://photofolio.s3.ap-northeast-2.amazonaws.com/1667808866893.png",
      "title": "11월 7일 14",
      "IFNULL(a.comment_cnt, '0')": "0",
      "IFNULL(b.sympathy_cnt, '0')": "0",
      "view_count": 0,
      "created_at": "2022-11-07"
    },
    {
      "id": 79,
      "nickname": "undefined",
      "profile_image": "https://photofolio.s3.ap-northeast-2.amazonaws.com/1667724350149.jpg",
      "img_url": "https://photofolio.s3.ap-northeast-2.amazonaws.com/1667808709496.png",
      "title": "11월 7일 13",
      "IFNULL(a.comment_cnt, '0')": "0",
      "IFNULL(b.sympathy_cnt, '0')": "0",
      "view_count": 0,
      "created_at": "2022-11-07"
    },
    {
      "id": 78,
      "nickname": "undefined",
      "profile_image": "https://photofolio.s3.ap-northeast-2.amazonaws.com/1667724350149.jpg",
      "img_url": "https://photofolio.s3.ap-northeast-2.amazonaws.com/1667808380875.png",
      "title": "11월 7일 12",
      "IFNULL(a.comment_cnt, '0')": "0",
      "IFNULL(b.sympathy_cnt, '0')": "0",
      "view_count": 0,
      "created_at": "2022-11-07"
    },
    {
      "id": 77,
      "nickname": "undefined",
      "profile_image": "https://photofolio.s3.ap-northeast-2.amazonaws.com/1667724350149.jpg",
      "img_url": "https://photofolio.s3.ap-northeast-2.amazonaws.com/1667808348436.png",
      "title": "11월 7일 11",
      "IFNULL(a.comment_cnt, '0')": "0",
      "IFNULL(b.sympathy_cnt, '0')": "0",
      "view_count": 0,
      "created_at": "2022-11-07"
    },
    {
      "id": 76,
      "nickname": "undefined",
      "profile_image": "https://photofolio.s3.ap-northeast-2.amazonaws.com/1667724350149.jpg",
      "img_url": "https://photofolio.s3.ap-northeast-2.amazonaws.com/1667807957149.png",
      "title": "11월 7일 10",
      "IFNULL(a.comment_cnt, '0')": "0",
      "IFNULL(b.sympathy_cnt, '0')": "0",
      "view_count": 0,
      "created_at": "2022-11-07"
    },
    {
      "id": 75,
      "nickname": "undefined",
      "profile_image": "https://photofolio.s3.ap-northeast-2.amazonaws.com/1667724350149.jpg",
      "img_url": "https://photofolio.s3.ap-northeast-2.amazonaws.com/1667807872316.png",
      "title": "11월 7일 9",
      "IFNULL(a.comment_cnt, '0')": "0",
      "IFNULL(b.sympathy_cnt, '0')": "0",
      "view_count": 0,
      "created_at": "2022-11-07"
    },
    {
      "id": 74,
      "nickname": "undefined",
      "profile_image": "https://photofolio.s3.ap-northeast-2.amazonaws.com/1667724350149.jpg",
      "img_url": "https://photofolio.s3.ap-northeast-2.amazonaws.com/1667807835570.png",
      "title": "11월 7일 8",
      "IFNULL(a.comment_cnt, '0')": "0",
      "IFNULL(b.sympathy_cnt, '0')": "0",
      "view_count": 0,
      "created_at": "2022-11-07"
    },
    {
      "id": 73,
      "nickname": "undefined",
      "profile_image": "https://photofolio.s3.ap-northeast-2.amazonaws.com/1667724350149.jpg",
      "img_url": "https://photofolio.s3.ap-northeast-2.amazonaws.com/1667807794451.png",
      "title": "11월 7일 7",
      "IFNULL(a.comment_cnt, '0')": "0",
      "IFNULL(b.sympathy_cnt, '0')": "0",
      "view_count": 0,
      "created_at": "2022-11-07"
    },
    {
      "id": 72,
      "nickname": "undefined",
      "profile_image": "https://photofolio.s3.ap-northeast-2.amazonaws.com/1667724350149.jpg",
      "img_url": "https://photofolio.s3.ap-northeast-2.amazonaws.com/1667807736507.png",
      "title": "11월 7일 6",
      "IFNULL(a.comment_cnt, '0')": "0",
      "IFNULL(b.sympathy_cnt, '0')": "0",
      "view_count": 0,
      "created_at": "2022-11-07"
    },
    {
      "id": 71,
      "nickname": "undefined",
      "profile_image": "https://photofolio.s3.ap-northeast-2.amazonaws.com/1667724350149.jpg",
      "img_url": "https://photofolio.s3.ap-northeast-2.amazonaws.com/1667807567200.png",
      "title": "11월 7일 5",
      "IFNULL(a.comment_cnt, '0')": "0",
      "IFNULL(b.sympathy_cnt, '0')": "0",
      "view_count": 0,
      "created_at": "2022-11-07"
    },
    {
      "id": 70,
      "nickname": "undefined",
      "profile_image": "https://photofolio.s3.ap-northeast-2.amazonaws.com/1667724350149.jpg",
      "img_url": "https://photofolio.s3.ap-northeast-2.amazonaws.com/1667807510334.png",
      "title": "11월 7일 4",
      "IFNULL(a.comment_cnt, '0')": "0",
      "IFNULL(b.sympathy_cnt, '0')": "0",
      "view_count": 0,
      "created_at": "2022-11-07"
    },
    {
      "id": 69,
      "nickname": "undefined",
      "profile_image": "https://photofolio.s3.ap-northeast-2.amazonaws.com/1667724350149.jpg",
      "img_url": "https://photofolio.s3.ap-northeast-2.amazonaws.com/1667807483961.png",
      "title": "11월 7일 3",
      "IFNULL(a.comment_cnt, '0')": "0",
      "IFNULL(b.sympathy_cnt, '0')": "0",
      "view_count": 0,
      "created_at": "2022-11-07"
    },
    {
      "id": 68,
      "nickname": "undefined",
      "profile_image": "https://photofolio.s3.ap-northeast-2.amazonaws.com/1667724350149.jpg",
      "img_url": "https://photofolio.s3.ap-northeast-2.amazonaws.com/1667807393670.png",
      "title": "11월 7일 2",
      "IFNULL(a.comment_cnt, '0')": "0",
      "IFNULL(b.sympathy_cnt, '0')": "0",
      "view_count": 0,
      "created_at": "2022-11-07"
    },
    {
      "id": 67,
      "nickname": "undefined",
      "profile_image": "https://photofolio.s3.ap-northeast-2.amazonaws.com/1667724350149.jpg",
      "img_url": "https://photofolio.s3.ap-northeast-2.amazonaws.com/1667807251880.png",
      "title": "11월 7일 1",
      "IFNULL(a.comment_cnt, '0')": "0",
      "IFNULL(b.sympathy_cnt, '0')": "0",
      "view_count": 0,
      "created_at": "2022-11-07"
    },
    {
      "id": 66,
      "nickname": "undefined",
      "profile_image": "https://photofolio.s3.ap-northeast-2.amazonaws.com/1667724350149.jpg",
      "img_url": "https://photofolio.s3.ap-northeast-2.amazonaws.com/1667796431444.png",
      "title": "11월 7일",
      "IFNULL(a.comment_cnt, '0')": "0",
      "IFNULL(b.sympathy_cnt, '0')": "0",
      "view_count": 0,
      "created_at": "2022-11-07"
    },
    {
      "id": 65,
      "nickname": "undefined",
      "profile_image": "https://photofolio.s3.ap-northeast-2.amazonaws.com/1667724350149.jpg",
      "img_url": "https://photofolio.s3.ap-northeast-2.amazonaws.com/1667791807019.png",
      "title": "안녕하세요! 테스트d14f2dddfdddㄹ",
      "IFNULL(a.comment_cnt, '0')": "0",
      "IFNULL(b.sympathy_cnt, '0')": "0",
      "view_count": 0,
      "created_at": "2022-11-07"
    },
    {
      "id": 64,
      "nickname": "undefined",
      "profile_image": "https://photofolio.s3.ap-northeast-2.amazonaws.com/1667724350149.jpg",
      "img_url": "https://photofolio.s3.ap-northeast-2.amazonaws.com/1667790746482.png",
      "title": "안녕하세요! 테스트d14f2ddddd",
      "IFNULL(a.comment_cnt, '0')": "0",
      "IFNULL(b.sympathy_cnt, '0')": "0",
      "view_count": 0,
      "created_at": "2022-11-07"
    },
    {
      "id": 63,
      "nickname": "undefined",
      "profile_image": "https://photofolio.s3.ap-northeast-2.amazonaws.com/1667724350149.jpg",
      "img_url": "https://photofolio.s3.ap-northeast-2.amazonaws.com/1667785670943.png",
      "title": "안녕하세요! 테스트d14f2dddddddd",
      "IFNULL(a.comment_cnt, '0')": "0",
      "IFNULL(b.sympathy_cnt, '0')": "0",
      "view_count": 0,
      "created_at": "2022-11-07"
    },
    {
      "id": 62,
      "nickname": "undefined",
      "profile_image": "https://photofolio.s3.ap-northeast-2.amazonaws.com/1667724350149.jpg",
      "img_url": "https://photofolio.s3.ap-northeast-2.amazonaws.com/1667785188710.png",
      "title": "안녕하세요! 테스트d14f2ddddddd",
      "IFNULL(a.comment_cnt, '0')": "0",
      "IFNULL(b.sympathy_cnt, '0')": "0",
      "view_count": 0,
      "created_at": "2022-11-07"
    },
    {
      "id": 61,
      "nickname": "undefined",
      "profile_image": "https://photofolio.s3.ap-northeast-2.amazonaws.com/1667724350149.jpg",
      "img_url": "https://photofolio.s3.ap-northeast-2.amazonaws.com/1667748403605.png",
      "title": "안녕하세요! 테스트14f2ddddddd",
      "IFNULL(a.comment_cnt, '0')": "0",
      "IFNULL(b.sympathy_cnt, '0')": "0",
      "view_count": 0,
      "created_at": "2022-11-07"
    },
    {
      "id": 60,
      "nickname": "undefined",
      "profile_image": "https://photofolio.s3.ap-northeast-2.amazonaws.com/1667724350149.jpg",
      "img_url": "https://photofolio.s3.ap-northeast-2.amazonaws.com/1667748318517.png",
      "title": "안녕하세요! 테스트14f2dddddd",
      "IFNULL(a.comment_cnt, '0')": "0",
      "IFNULL(b.sympathy_cnt, '0')": "0",
      "view_count": 0,
      "created_at": "2022-11-07"
    },
    {
      "id": 59,
      "nickname": "undefined",
      "profile_image": "https://photofolio.s3.ap-northeast-2.amazonaws.com/1667724350149.jpg",
      "img_url": "https://photofolio.s3.ap-northeast-2.amazonaws.com/1667748300461.png",
      "title": "안녕하세요! 테스트14f2ddddd",
      "IFNULL(a.comment_cnt, '0')": "0",
      "IFNULL(b.sympathy_cnt, '0')": "0",
      "view_count": 0,
      "created_at": "2022-11-07"
    },
    {
      "id": 58,
      "nickname": "undefined",
      "profile_image": "https://photofolio.s3.ap-northeast-2.amazonaws.com/1667724350149.jpg",
      "img_url": "https://photofolio.s3.ap-northeast-2.amazonaws.com/1667748260376.png",
      "title": "안녕하세요! 테스트14f2dddd",
      "IFNULL(a.comment_cnt, '0')": "0",
      "IFNULL(b.sympathy_cnt, '0')": "0",
      "view_count": 0,
      "created_at": "2022-11-07"
    },
    {
      "id": 57,
      "nickname": "undefined",
      "profile_image": "https://photofolio.s3.ap-northeast-2.amazonaws.com/1667724350149.jpg",
      "img_url": "https://photofolio.s3.ap-northeast-2.amazonaws.com/1667748226107.png",
      "title": "안녕하세요! 테스트14f2ddd",
      "IFNULL(a.comment_cnt, '0')": "0",
      "IFNULL(b.sympathy_cnt, '0')": "0",
      "view_count": 0,
      "created_at": "2022-11-07"
    },
    {
      "id": 56,
      "nickname": "undefined",
      "profile_image": "https://photofolio.s3.ap-northeast-2.amazonaws.com/1667724350149.jpg",
      "img_url": "https://photofolio.s3.ap-northeast-2.amazonaws.com/1667748016282.png",
      "title": "안녕하세요! 테스트14f2dd",
      "IFNULL(a.comment_cnt, '0')": "0",
      "IFNULL(b.sympathy_cnt, '0')": "0",
      "view_count": 0,
      "created_at": "2022-11-07"
    },
    {
      "id": 55,
      "nickname": "undefined",
      "profile_image": "https://photofolio.s3.ap-northeast-2.amazonaws.com/1667724350149.jpg",
      "img_url": "https://photofolio.s3.ap-northeast-2.amazonaws.com/1667747801130.png",
      "title": "안녕하세요! 테스트14f2d",
      "IFNULL(a.comment_cnt, '0')": "0",
      "IFNULL(b.sympathy_cnt, '0')": "0",
      "view_count": 0,
      "created_at": "2022-11-07"
    },
    {
      "id": 54,
      "nickname": "undefined",
      "profile_image": "https://photofolio.s3.ap-northeast-2.amazonaws.com/1667724350149.jpg",
      "img_url": "https://photofolio.s3.ap-northeast-2.amazonaws.com/1667747742264.png",
      "title": "안녕하세요! 테스트14f2",
      "IFNULL(a.comment_cnt, '0')": "0",
      "IFNULL(b.sympathy_cnt, '0')": "0",
      "view_count": 0,
      "created_at": "2022-11-07"
    },
    {
      "id": 53,
      "nickname": "undefined",
      "profile_image": "https://photofolio.s3.ap-northeast-2.amazonaws.com/1667724350149.jpg",
      "img_url": "https://photofolio.s3.ap-northeast-2.amazonaws.com/1667747678784.png",
      "title": "안녕하세요! 테스트14f",
      "IFNULL(a.comment_cnt, '0')": "0",
      "IFNULL(b.sympathy_cnt, '0')": "0",
      "view_count": 0,
      "created_at": "2022-11-07"
    },
    {
      "id": 52,
      "nickname": "undefined",
      "profile_image": "https://photofolio.s3.ap-northeast-2.amazonaws.com/1667724350149.jpg",
      "img_url": "https://photofolio.s3.ap-northeast-2.amazonaws.com/1667747234935.png",
      "title": "안녕하세요! 테스트13ddddssdsdddd",
      "IFNULL(a.comment_cnt, '0')": "0",
      "IFNULL(b.sympathy_cnt, '0')": "0",
      "view_count": 0,
      "created_at": "2022-11-07"
    },
    {
      "id": 51,
      "nickname": "undefined",
      "profile_image": "https://photofolio.s3.ap-northeast-2.amazonaws.com/1667724350149.jpg",
      "img_url": "https://photofolio.s3.ap-northeast-2.amazonaws.com/1667747186517.png",
      "title": "안녕하세요! 테스트13ddddssdsddd",
      "IFNULL(a.comment_cnt, '0')": "0",
      "IFNULL(b.sympathy_cnt, '0')": "0",
      "view_count": 0,
      "created_at": "2022-11-07"
    },
    {
      "id": 50,
      "nickname": "undefined",
      "profile_image": "https://photofolio.s3.ap-northeast-2.amazonaws.com/1667724350149.jpg",
      "img_url": "https://photofolio.s3.ap-northeast-2.amazonaws.com/1667747108163.png",
      "title": "안녕하세요! 테스트13ddddssdsdd",
      "IFNULL(a.comment_cnt, '0')": "0",
      "IFNULL(b.sympathy_cnt, '0')": "0",
      "view_count": 0,
      "created_at": "2022-11-07"
    },
    {
      "id": 49,
      "nickname": "undefined",
      "profile_image": "https://photofolio.s3.ap-northeast-2.amazonaws.com/1667724350149.jpg",
      "img_url": "https://photofolio.s3.ap-northeast-2.amazonaws.com/1667747074736.png",
      "title": "안녕하세요! 테스트13ddddssdsd",
      "IFNULL(a.comment_cnt, '0')": "0",
      "IFNULL(b.sympathy_cnt, '0')": "0",
      "view_count": 0,
      "created_at": "2022-11-07"
    },
    {
      "id": 48,
      "nickname": "undefined",
      "profile_image": "https://photofolio.s3.ap-northeast-2.amazonaws.com/1667724350149.jpg",
      "img_url": "https://photofolio.s3.ap-northeast-2.amazonaws.com/1667747030367.png",
      "title": "안녕하세요! 테스트13ddddssds",
      "IFNULL(a.comment_cnt, '0')": "0",
      "IFNULL(b.sympathy_cnt, '0')": "0",
      "view_count": 0,
      "created_at": "2022-11-07"
    },
    {
      "id": 47,
      "nickname": "undefined",
      "profile_image": "https://photofolio.s3.ap-northeast-2.amazonaws.com/1667724350149.jpg",
      "img_url": "https://photofolio.s3.ap-northeast-2.amazonaws.com/1667746892024.png",
      "title": "안녕하세요! 테스트13dddssds",
      "IFNULL(a.comment_cnt, '0')": "0",
      "IFNULL(b.sympathy_cnt, '0')": "0",
      "view_count": 0,
      "created_at": "2022-11-07"
    },
    {
      "id": 46,
      "nickname": "undefined",
      "profile_image": "https://photofolio.s3.ap-northeast-2.amazonaws.com/1667724350149.jpg",
      "img_url": "https://photofolio.s3.ap-northeast-2.amazonaws.com/1667746545259.png",
      "title": "안녕하세요! 테스트13dddssd",
      "IFNULL(a.comment_cnt, '0')": "0",
      "IFNULL(b.sympathy_cnt, '0')": "0",
      "view_count": 0,
      "created_at": "2022-11-06"
    },
    {
      "id": 45,
      "nickname": "undefined",
      "profile_image": "https://photofolio.s3.ap-northeast-2.amazonaws.com/1667724350149.jpg",
      "img_url": "https://photofolio.s3.ap-northeast-2.amazonaws.com/1667746477956.png",
      "title": "안녕하세요! 테스트13dddss",
      "IFNULL(a.comment_cnt, '0')": "0",
      "IFNULL(b.sympathy_cnt, '0')": "0",
      "view_count": 0,
      "created_at": "2022-11-06"
    },
    {
      "id": 44,
      "nickname": "undefined",
      "profile_image": "https://photofolio.s3.ap-northeast-2.amazonaws.com/1667724350149.jpg",
      "img_url": "https://photofolio.s3.ap-northeast-2.amazonaws.com/1667746452564.png",
      "title": "안녕하세요! 테스트13ddddddd",
      "IFNULL(a.comment_cnt, '0')": "0",
      "IFNULL(b.sympathy_cnt, '0')": "0",
      "view_count": 0,
      "created_at": "2022-11-06"
    },
    {
      "id": 43,
      "nickname": "undefined",
      "profile_image": "https://photofolio.s3.ap-northeast-2.amazonaws.com/1667724350149.jpg",
      "img_url": "https://photofolio.s3.ap-northeast-2.amazonaws.com/1667746420172.png",
      "title": "안녕하세요! 테스트13dddddd",
      "IFNULL(a.comment_cnt, '0')": "0",
      "IFNULL(b.sympathy_cnt, '0')": "0",
      "view_count": 0,
      "created_at": "2022-11-06"
    },
    {
      "id": 42,
      "nickname": "undefined",
      "profile_image": "https://photofolio.s3.ap-northeast-2.amazonaws.com/1667724350149.jpg",
      "img_url": "https://photofolio.s3.ap-northeast-2.amazonaws.com/1667746367721.png",
      "title": "안녕하세요! 테스트13ddddd",
      "IFNULL(a.comment_cnt, '0')": "0",
      "IFNULL(b.sympathy_cnt, '0')": "0",
      "view_count": 0,
      "created_at": "2022-11-06"
    },
    {
      "id": 41,
      "nickname": "undefined",
      "profile_image": "https://photofolio.s3.ap-northeast-2.amazonaws.com/1667724350149.jpg",
      "img_url": "https://photofolio.s3.ap-northeast-2.amazonaws.com/1667746299229.png",
      "title": "안녕하세요! 테스트13dddd",
      "IFNULL(a.comment_cnt, '0')": "0",
      "IFNULL(b.sympathy_cnt, '0')": "0",
      "view_count": 0,
      "created_at": "2022-11-06"
    },
    {
      "id": 40,
      "nickname": "undefined",
      "profile_image": "https://photofolio.s3.ap-northeast-2.amazonaws.com/1667724350149.jpg",
      "img_url": "https://photofolio.s3.ap-northeast-2.amazonaws.com/1667746269184.png",
      "title": "안녕하세요! 테스트13ddd",
      "IFNULL(a.comment_cnt, '0')": "0",
      "IFNULL(b.sympathy_cnt, '0')": "0",
      "view_count": 0,
      "created_at": "2022-11-06"
    },
    {
      "id": 39,
      "nickname": "undefined",
      "profile_image": "https://photofolio.s3.ap-northeast-2.amazonaws.com/1667724350149.jpg",
      "img_url": "https://photofolio.s3.ap-northeast-2.amazonaws.com/1667746147927.png",
      "title": "안녕하세요! 테스트13dd",
      "IFNULL(a.comment_cnt, '0')": "0",
      "IFNULL(b.sympathy_cnt, '0')": "0",
      "view_count": 0,
      "created_at": "2022-11-06"
    },
    {
      "id": 38,
      "nickname": "undefined",
      "profile_image": "https://photofolio.s3.ap-northeast-2.amazonaws.com/1667724350149.jpg",
      "img_url": "https://photofolio.s3.ap-northeast-2.amazonaws.com/1667746100681.png",
      "title": "안녕하세요! 테스트13d",
      "IFNULL(a.comment_cnt, '0')": "0",
      "IFNULL(b.sympathy_cnt, '0')": "0",
      "view_count": 0,
      "created_at": "2022-11-06"
    },
    {
      "id": 37,
      "nickname": "undefined",
      "profile_image": "https://photofolio.s3.ap-northeast-2.amazonaws.com/1667724350149.jpg",
      "img_url": "https://photofolio.s3.ap-northeast-2.amazonaws.com/1667745969918.png",
      "title": "안녕하세요! 테스트13",
      "IFNULL(a.comment_cnt, '0')": "0",
      "IFNULL(b.sympathy_cnt, '0')": "0",
      "view_count": 0,
      "created_at": "2022-11-06"
    },
    {
      "id": 36,
      "nickname": "undefined",
      "profile_image": "https://photofolio.s3.ap-northeast-2.amazonaws.com/1667724350149.jpg",
      "img_url": "https://photofolio.s3.ap-northeast-2.amazonaws.com/1667735670372.png",
      "title": "안녕하세요! 테스트12456f",
      "IFNULL(a.comment_cnt, '0')": "0",
      "IFNULL(b.sympathy_cnt, '0')": "0",
      "view_count": 0,
      "created_at": "2022-11-06"
    },
    {
      "id": 35,
      "nickname": "undefined",
      "profile_image": "https://photofolio.s3.ap-northeast-2.amazonaws.com/1667724350149.jpg",
      "img_url": "https://photofolio.s3.ap-northeast-2.amazonaws.com/1667733653657.jpg",
      "title": "안녕하세요! 테스트12456",
      "IFNULL(a.comment_cnt, '0')": "0",
      "IFNULL(b.sympathy_cnt, '0')": "0",
      "view_count": 0,
      "created_at": "2022-11-06"
    },
    {
      "id": 34,
      "nickname": "undefined",
      "profile_image": "https://photofolio.s3.ap-northeast-2.amazonaws.com/1667724350149.jpg",
      "img_url": "https://photofolio.s3.ap-northeast-2.amazonaws.com/1667730454098.jpg",
      "title": "안녕하세요! 테스트124",
      "IFNULL(a.comment_cnt, '0')": "0",
      "IFNULL(b.sympathy_cnt, '0')": "0",
      "view_count": 0,
      "created_at": "2022-11-06"
    },
    {
      "id": 33,
      "nickname": "undefined",
      "profile_image": "https://photofolio.s3.ap-northeast-2.amazonaws.com/1667724350149.jpg",
      "img_url": null,
      "title": "안녕하세요! 테스트12",
      "IFNULL(a.comment_cnt, '0')": "0",
      "IFNULL(b.sympathy_cnt, '0')": "0",
      "view_count": 0,
      "created_at": "2022-11-06"
    },
    {
      "id": 32,
      "nickname": "undefined",
      "profile_image": "https://photofolio.s3.ap-northeast-2.amazonaws.com/1667724350149.jpg",
      "img_url": null,
      "title": "안녕하세요! 테스트123",
      "IFNULL(a.comment_cnt, '0')": "0",
      "IFNULL(b.sympathy_cnt, '0')": "0",
      "view_count": 0,
      "created_at": "2022-11-06"
    },
    {
      "id": 31,
      "nickname": "undefined",
      "profile_image": "https://photofolio.s3.ap-northeast-2.amazonaws.com/1667724350149.jpg",
      "img_url": "https://photofolio.s3.ap-northeast-2.amazonaws.com/1667730300702.jpg",
      "title": "안녕하세요! 테스트123",
      "IFNULL(a.comment_cnt, '0')": "0",
      "IFNULL(b.sympathy_cnt, '0')": "0",
      "view_count": 0,
      "created_at": "2022-11-06"
    },
    {
      "id": 30,
      "nickname": "undefined",
      "profile_image": "https://photofolio.s3.ap-northeast-2.amazonaws.com/1667724350149.jpg",
      "img_url": null,
      "title": "안녕하세요! 테스트12",
      "IFNULL(a.comment_cnt, '0')": "0",
      "IFNULL(b.sympathy_cnt, '0')": "0",
      "view_count": 0,
      "created_at": "2022-11-06"
    },
    {
      "id": 29,
      "nickname": "undefined",
      "profile_image": "https://photofolio.s3.ap-northeast-2.amazonaws.com/1667724350149.jpg",
      "img_url": null,
      "title": "안녕하세요! 테스트12",
      "IFNULL(a.comment_cnt, '0')": "0",
      "IFNULL(b.sympathy_cnt, '0')": "0",
      "view_count": 0,
      "created_at": "2022-11-06"
    },
    {
      "id": 28,
      "nickname": "undefined",
      "profile_image": "https://photofolio.s3.ap-northeast-2.amazonaws.com/1667724350149.jpg",
      "img_url": null,
      "title": "안녕하세요! 테스트12",
      "IFNULL(a.comment_cnt, '0')": "0",
      "IFNULL(b.sympathy_cnt, '0')": "0",
      "view_count": 0,
      "created_at": "2022-11-06"
    },
    {
      "id": 27,
      "nickname": "undefined",
      "profile_image": "https://photofolio.s3.ap-northeast-2.amazonaws.com/1667724350149.jpg",
      "img_url": null,
      "title": "안녕하세요! 테스트12",
      "IFNULL(a.comment_cnt, '0')": "0",
      "IFNULL(b.sympathy_cnt, '0')": "0",
      "view_count": 0,
      "created_at": "2022-11-06"
    },
    {
      "id": 26,
      "nickname": "undefined",
      "profile_image": "https://photofolio.s3.ap-northeast-2.amazonaws.com/1667724350149.jpg",
      "img_url": "https://photofolio.s3.ap-northeast-2.amazonaws.com/1667730347575.jpg",
      "title": "안녕하세요! 테스트12",
      "IFNULL(a.comment_cnt, '0')": "0",
      "IFNULL(b.sympathy_cnt, '0')": "0",
      "view_count": 0,
      "created_at": "2022-11-06"
    },
    {
      "id": 25,
      "nickname": "undefined",
      "profile_image": "https://photofolio.s3.ap-northeast-2.amazonaws.com/1667724350149.jpg",
      "img_url": null,
      "title": "안녕하세요! 테스트1",
      "IFNULL(a.comment_cnt, '0')": "0",
      "IFNULL(b.sympathy_cnt, '0')": "0",
      "view_count": 0,
      "created_at": "2022-11-06"
    },
    {
      "id": 24,
      "nickname": "undefined",
      "profile_image": "https://photofolio.s3.ap-northeast-2.amazonaws.com/1667724350149.jpg",
      "img_url": null,
      "title": "안녕하세요! 테스트1",
      "IFNULL(a.comment_cnt, '0')": "0",
      "IFNULL(b.sympathy_cnt, '0')": "0",
      "view_count": 0,
      "created_at": "2022-11-06"
    },
    {
      "id": 23,
      "nickname": "undefined",
      "profile_image": "https://photofolio.s3.ap-northeast-2.amazonaws.com/1667724350149.jpg",
      "img_url": null,
      "title": "안녕하세요! 테스트1",
      "IFNULL(a.comment_cnt, '0')": "0",
      "IFNULL(b.sympathy_cnt, '0')": "0",
      "view_count": 0,
      "created_at": "2022-11-06"
    },
    {
      "id": 22,
      "nickname": "undefined",
      "profile_image": "https://photofolio.s3.ap-northeast-2.amazonaws.com/1667724350149.jpg",
      "img_url": null,
      "title": "안녕하세요! 테스트1",
      "IFNULL(a.comment_cnt, '0')": "0",
      "IFNULL(b.sympathy_cnt, '0')": "0",
      "view_count": 0,
      "created_at": "2022-11-06"
    },
    {
      "id": 21,
      "nickname": "undefined",
      "profile_image": "https://photofolio.s3.ap-northeast-2.amazonaws.com/1667724350149.jpg",
      "img_url": "https://photofolio.s3.ap-northeast-2.amazonaws.com/1667729372661.jpg",
      "title": "안녕하세요! 테스트1",
      "IFNULL(a.comment_cnt, '0')": "0",
      "IFNULL(b.sympathy_cnt, '0')": "0",
      "view_count": 0,
      "created_at": "2022-11-06"
    },
    {
      "id": 20,
      "nickname": "undefined",
      "profile_image": "https://photofolio.s3.ap-northeast-2.amazonaws.com/1667724350149.jpg",
      "img_url": null,
      "title": "안녕하세요",
      "IFNULL(a.comment_cnt, '0')": "0",
      "IFNULL(b.sympathy_cnt, '0')": "0",
      "view_count": 0,
      "created_at": "2022-11-06"
    },
    {
      "id": 19,
      "nickname": "undefined",
      "profile_image": "https://photofolio.s3.ap-northeast-2.amazonaws.com/1667724350149.jpg",
      "img_url": null,
      "title": "안녕하세요",
      "IFNULL(a.comment_cnt, '0')": "0",
      "IFNULL(b.sympathy_cnt, '0')": "0",
      "view_count": 4,
      "created_at": "2022-11-06"
    },
    {
      "id": 18,
      "nickname": "undefined",
      "profile_image": "https://photofolio.s3.ap-northeast-2.amazonaws.com/1667724350149.jpg",
      "img_url": null,
      "title": "안녕하세요",
      "IFNULL(a.comment_cnt, '0')": "0",
      "IFNULL(b.sympathy_cnt, '0')": "0",
      "view_count": 8,
      "created_at": "2022-11-06"
    },
    {
      "id": 17,
      "nickname": "undefined",
      "profile_image": "https://photofolio.s3.ap-northeast-2.amazonaws.com/1667724350149.jpg",
      "img_url": "https://photofolio.s3.ap-northeast-2.amazonaws.com/1667728001429.jpg",
      "title": "안녕하세요",
      "IFNULL(a.comment_cnt, '0')": "0",
      "IFNULL(b.sympathy_cnt, '0')": "0",
      "view_count": 24,
      "created_at": "2022-11-06"
    },
    {
      "id": 16,
      "nickname": "한국",
      "profile_image": "12345678",
      "img_url": null,
      "title": "포스팅15",
      "IFNULL(a.comment_cnt, '0')": "0",
      "IFNULL(b.sympathy_cnt, '0')": "0",
      "view_count": 0,
      "created_at": "2022-11-05"
    },
    {
      "id": 15,
      "nickname": "미국",
      "profile_image": "http://profile1",
      "img_url": null,
      "title": "포스팅15",
      "IFNULL(a.comment_cnt, '0')": "0",
      "IFNULL(b.sympathy_cnt, '0')": "0",
      "view_count": 457,
      "created_at": "2022-11-05"
    },
    {
      "id": 14,
      "nickname": null,
      "profile_image": "https://photofolio.s3.ap-northeast-2.amazonaws.com/1667562399381.jpg",
      "img_url": null,
      "title": "포스팅14",
      "IFNULL(a.comment_cnt, '0')": "0",
      "IFNULL(b.sympathy_cnt, '0')": "0",
      "view_count": 346,
      "created_at": "2022-11-05"
    },
    {
      "id": 13,
      "nickname": "undefined",
      "profile_image": "https://photofolio.s3.ap-northeast-2.amazonaws.com/1667581426590.jpg",
      "img_url": null,
      "title": "포스팅13",
      "IFNULL(a.comment_cnt, '0')": "0",
      "IFNULL(b.sympathy_cnt, '0')": "0",
      "view_count": 65723,
      "created_at": "2022-11-05"
    },
    {
      "id": 12,
      "nickname": null,
      "profile_image": "https://photofolio.s3.ap-northeast-2.amazonaws.com/1667562399381.jpg",
      "img_url": null,
      "title": "포스팅12",
      "IFNULL(a.comment_cnt, '0')": "0",
      "IFNULL(b.sympathy_cnt, '0')": "0",
      "view_count": 346,
      "created_at": "2022-11-05"
    },
    {
      "id": 11,
      "nickname": null,
      "profile_image": "https://photofolio.s3.ap-northeast-2.amazonaws.com/1667561520666.jpg",
      "img_url": null,
      "title": "포스팅11",
      "IFNULL(a.comment_cnt, '0')": "0",
      "IFNULL(b.sympathy_cnt, '0')": "0",
      "view_count": 234,
      "created_at": "2022-11-05"
    },
    {
      "id": 10,
      "nickname": "미국",
      "profile_image": "",
      "img_url": "https://photofolio.s3.ap-northeast-2.amazonaws.com/1667568678786.jpg",
      "title": "포스팅10",
      "IFNULL(a.comment_cnt, '0')": "0",
      "IFNULL(b.sympathy_cnt, '0')": "0",
      "view_count": 230587,
      "created_at": "2022-11-05"
    },
    {
      "id": 9,
      "nickname": "한국",
      "profile_image": "12345678",
      "img_url": null,
      "title": "포스팅9",
      "IFNULL(a.comment_cnt, '0')": "0",
      "IFNULL(b.sympathy_cnt, '0')": "0",
      "view_count": 2307,
      "created_at": "2022-11-05"
    },
    {
      "id": 8,
      "nickname": "미국",
      "profile_image": "http://profile1",
      "img_url": "https://photofolio.s3.ap-northeast-2.amazonaws.com/1667568678768.jpg",
      "title": "포스팅8",
      "IFNULL(a.comment_cnt, '0')": "0",
      "IFNULL(b.sympathy_cnt, '0')": "0",
      "view_count": 23095,
      "created_at": "2022-11-05"
    },
    {
      "id": 7,
      "nickname": "미국",
      "profile_image": "http://profile1",
      "img_url": null,
      "title": "포스팅7",
      "IFNULL(a.comment_cnt, '0')": "0",
      "IFNULL(b.sympathy_cnt, '0')": "0",
      "view_count": 7679,
      "created_at": "2022-11-05"
    },
    {
      "id": 6,
      "nickname": "미국",
      "profile_image": "http://profile1",
      "img_url": null,
      "title": "포스팅6",
      "IFNULL(a.comment_cnt, '0')": "0",
      "IFNULL(b.sympathy_cnt, '0')": "0",
      "view_count": 48,
      "created_at": "2022-11-05"
    },
    {
      "id": 5,
      "nickname": "국적",
      "profile_image": "",
      "img_url": null,
      "title": "포스팅5",
      "IFNULL(a.comment_cnt, '0')": "0",
      "IFNULL(b.sympathy_cnt, '0')": "0",
      "view_count": 80,
      "created_at": "2022-11-05"
    },
    {
      "id": 4,
      "nickname": "한국",
      "profile_image": "12345678",
      "img_url": null,
      "title": "포스팅4",
      "IFNULL(a.comment_cnt, '0')": "0",
      "IFNULL(b.sympathy_cnt, '0')": "0",
      "view_count": 59,
      "created_at": "2022-11-05"
    },
    {
      "id": 3,
      "nickname": "미국",
      "profile_image": "http://profile1",
      "img_url": null,
      "title": "포스팅3",
      "IFNULL(a.comment_cnt, '0')": "0",
      "IFNULL(b.sympathy_cnt, '0')": "0",
      "view_count": 14,
      "created_at": "2022-11-05"
    },
    {
      "id": 2,
      "nickname": "미국",
      "profile_image": "http://profile1",
      "img_url": null,
      "title": "포스팅2",
      "IFNULL(a.comment_cnt, '0')": "0",
      "IFNULL(b.sympathy_cnt, '0')": "0",
      "view_count": 12,
      "created_at": "2022-11-05"
    },
    {
      "id": 1,
      "nickname": "미국",
      "profile_image": "http://profile1",
      "img_url": "https://photofolio.s3.ap-northeast-2.amazonaws.com/1667568678822.jpg",
      "title": "포스팅1",
      "IFNULL(a.comment_cnt, '0')": "0",
      "IFNULL(b.sympathy_cnt, '0')": "0",
      "view_count": 10,
      "created_at": "2022-11-04"
    }
  ]
}
